nrgten/__init__.py
nrgten/anm.py
nrgten/atom.py
nrgten/encom.py
nrgten/enm.py
nrgten/eq_filler.py
nrgten/func_writer.py
nrgten/macromol.py
nrgten/massdef.py
nrgten/metrics.py
nrgten/parser.py
nrgten/residue_list.py
nrgten/vcontacts_wrapper.py
nrgten/config/amino_acids.atomtypes
nrgten/config/amino_acids.masses
nrgten/config/ribonucleic_acids.atomtypes
nrgten/config/ribonucleic_acids.masses
nrgten/config/ribonucleic_acids_1n.atomtypes
nrgten/config/ribonucleic_acids_1n.masses
nrgten/vcontacts/Vcontacts-v1.2_for_python.c
nrgten/vcontacts/Vcontacts-v1.2_for_python_windows.c
nrgten/vcontacts/Vpoly.h
nrgten-1.0.dist-info/METADATA
nrgten-1.0.dist-info/RECORD
nrgten-1.0.dist-info/WHEEL
nrgten-1.0.dist-info/top_level.txt
