Metadata-Version: 2.1
Name: nrgten
Version: 1.0
Summary: Najmanovich Research Group Toolkit for Elastic Networks
Home-page: https://github.com/gregorpatof/nrgten_package
Author: Olivier Mailhot
License: UNKNOWN
Platform: UNKNOWN
Classifier: Programming Language :: Python :: 3
Classifier: License :: OSI Approved :: MIT License
Classifier: Operating System :: OS Independent
Requires-Python: >=3.6
Requires-Dist: numpy
